mappertrac/__init__.py
mappertrac/cli.py
mappertrac/data/container/README.md
mappertrac/data/container/bedpostx_postproc_gpu.sh
mappertrac/data/container/build.sh
mappertrac/data/container/datalad.def
mappertrac/data/container/freesurfer_v7.3.2.def
mappertrac/data/container/fsl_v6.0.6.4.def
mappertrac/data/container/mrtrix3.def
mappertrac/data/datalad/datalad_get_samples.sh
mappertrac/data/example_inputs/sub-011591/anat/sub-011591_T1w.nii.gz
mappertrac/data/example_inputs/sub-011591/dwi/sub-011591_dwi.bval
mappertrac/data/example_inputs/sub-011591/dwi/sub-011591_dwi.bvec
mappertrac/data/example_inputs/sub-011591/dwi/sub-011591_dwi.nii.gz
mappertrac/data/lists/connectome_idxs.txt
mappertrac/data/lists/list_edges_all.txt
mappertrac/data/lists/list_edges_reduced.txt
mappertrac/data/lists/list_edges_tiny.txt
mappertrac/subscripts/__init__.py
mappertrac/subscripts/s1_freesurfer.py
mappertrac/subscripts/s2_bedpostx.py
mappertrac/subscripts/s2b_mrtrix.py
mappertrac/subscripts/s3_probtrackx.py
mappertrac/subscripts/utilities.py
tests/__init__.py
tests/integration_tests.py
tests/unit_tests.py
mappertrac-1.3.1.dist-info/LICENSE
mappertrac-1.3.1.dist-info/METADATA
mappertrac-1.3.1.dist-info/NOTICE
mappertrac-1.3.1.dist-info/WHEEL
mappertrac-1.3.1.dist-info/entry_points.txt
mappertrac-1.3.1.dist-info/top_level.txt
mappertrac-1.3.1.dist-info/RECORD
