Metadata-Version: 2.1
Name: mappertrac
Version: 1.3.1
Summary: Probabilistic tractography for high-performance computing
Author: Joseph Moon
Author-email: moon15@llnl.gov
Classifier: Development Status :: 4 - Beta
Classifier: License :: OSI Approved :: BSD License
Classifier: Operating System :: POSIX :: Linux
Classifier: Topic :: Scientific/Engineering :: Bio-Informatics
Classifier: Topic :: System :: Distributed Computing
Classifier: Programming Language :: Python
Classifier: Programming Language :: Python :: 3
Classifier: Programming Language :: Python :: 3 :: Only
Classifier: Programming Language :: Python :: 3.7
Classifier: Programming Language :: Python :: 3.8
Classifier: Programming Language :: Python :: 3.9
Requires-Python: >=3.7
License-File: LICENSE
License-File: NOTICE
Requires-Dist: pip (>=21.2.4)
Requires-Dist: parsl (>=1.1.0)
Requires-Dist: pytest (>=6.2.4)
Requires-Dist: pytest-cov (>=3.0.0)
Requires-Dist: scipy (>=1.7.1)
Requires-Dist: numpy (>=1.21.2)
Requires-Dist: gputil (>=1.4.0)
